span/ipsec.secrets.sample
span/properties.py
span/setup.py
span/span.py
span/tutorial.py
span/span.data/ca.cert.pem
span/span.data/ca.key.pem
span/span.data/charon.conf
span/span.data/client.key.pem
span/span.data/client.pub.pem
span/span.data/ipsec.conf
span/span.data/server.key.pem
span/span.data/server.pub.pem
span/span.data/setup
span_cli-1.2.10.dist-info/METADATA
span_cli-1.2.10.dist-info/WHEEL
span_cli-1.2.10.dist-info/entry_points.txt
span_cli-1.2.10.dist-info/top_level.txt
span_cli-1.2.10.dist-info/RECORD
