Metadata-Version: 2.1
Name: span-cli
Version: 1.2.10
Requires-Dist: paramiko (==2.11.0)
Requires-Dist: requests (==2.25.1)
Requires-Dist: rich (==12.4.1)
Requires-Dist: scp (==0.13.6)
Requires-Dist: pyreadline (==2.1) ; platform_system == "Windows"
